processligandpy/__init__.py
processligandpy/processligand_wrapper.py
processligandpy/bin/ProcessLigand
processligandpy/lib64/cmake/openbabel3/OpenBabel3Config.cmake
processligandpy/lib64/cmake/openbabel3/OpenBabel3ConfigVersion.cmake
processligandpy/lib64/cmake/openbabel3/OpenBabel3_EXPORTS-release.cmake
processligandpy/lib64/cmake/openbabel3/OpenBabel3_EXPORTS.cmake
processligandpy/share/openbabel/3.1.1/MACCS.txt
processligandpy/share/openbabel/3.1.1/SMARTS_InteLigand.txt
processligandpy/share/openbabel/3.1.1/UFF.prm
processligandpy/share/openbabel/3.1.1/atomization-energies.txt
processligandpy/share/openbabel/3.1.1/atomtyp.txt
processligandpy/share/openbabel/3.1.1/babel_povray3.inc
processligandpy/share/openbabel/3.1.1/bondtyp.txt
processligandpy/share/openbabel/3.1.1/eem.txt
processligandpy/share/openbabel/3.1.1/eem2015ba.txt
processligandpy/share/openbabel/3.1.1/eem2015bm.txt
processligandpy/share/openbabel/3.1.1/eem2015bn.txt
processligandpy/share/openbabel/3.1.1/eem2015ha.txt
processligandpy/share/openbabel/3.1.1/eem2015hm.txt
processligandpy/share/openbabel/3.1.1/eem2015hn.txt
processligandpy/share/openbabel/3.1.1/eqeqIonizations.txt
processligandpy/share/openbabel/3.1.1/gaff.dat
processligandpy/share/openbabel/3.1.1/gaff.prm
processligandpy/share/openbabel/3.1.1/ghemical.prm
processligandpy/share/openbabel/3.1.1/logp.txt
processligandpy/share/openbabel/3.1.1/mmff94.ff
processligandpy/share/openbabel/3.1.1/mmff94s.ff
processligandpy/share/openbabel/3.1.1/mmffang.par
processligandpy/share/openbabel/3.1.1/mmffbndk.par
processligandpy/share/openbabel/3.1.1/mmffbond.par
processligandpy/share/openbabel/3.1.1/mmffchg.par
processligandpy/share/openbabel/3.1.1/mmffdef.par
processligandpy/share/openbabel/3.1.1/mmffdfsb.par
processligandpy/share/openbabel/3.1.1/mmffoop.par
processligandpy/share/openbabel/3.1.1/mmffpbci.par
processligandpy/share/openbabel/3.1.1/mmffprop.par
processligandpy/share/openbabel/3.1.1/mmffs_oop.par
processligand_py-1.0.4.dist-info/METADATA
processligand_py-1.0.4.dist-info/WHEEL
processligand_py-1.0.4.dist-info/RECORD
