Metadata-Version: 2.2
Name: processligand-py
Version: 1.0.4
Summary: Python wheels and a wrapper for ProcessLigand, a tool to prepare target and ligand files for FlexAID
Author: Thomas DesCôteaux
Author-Email: Rafael Najmanovich <rafael.najmanovich@umontreal.ca>
Classifier: Intended Audience :: Science/Research
Classifier: License :: OSI Approved :: GNU General Public License v3 or later (GPLv3+)
Classifier: Natural Language :: English
Project-URL: Homepage, https://github.com/NRGlab
Project-URL: Documentation, https://github.com/NRGlab/processligand-py/blob/main/README.md
Project-URL: Repository, https://github.com/NRGlab/processligand-py
Project-URL: Issues, https://github.com/NRGlab/processligand-py/issues
Requires-Python: >=3.9
